CHANGES.txt
CONTRIBUTORS.txt
MANIFEST.in
README.rst
bootstrap.py
buildout.cfg
setup.py
docs/LICENSE.GPL
docs/LICENSE.txt
src/collective/__init__.py
src/collective.lesscss.egg-info/PKG-INFO
src/collective.lesscss.egg-info/SOURCES.txt
src/collective.lesscss.egg-info/dependency_links.txt
src/collective.lesscss.egg-info/entry_points.txt
src/collective.lesscss.egg-info/namespace_packages.txt
src/collective.lesscss.egg-info/not-zip-safe
src/collective.lesscss.egg-info/requires.txt
src/collective.lesscss.egg-info/top_level.txt
src/collective/lesscss/__init__.py
src/collective/lesscss/configure.zcml
src/collective/lesscss/interface.py
src/collective/lesscss/overrides.zcml
src/collective/lesscss/testing.py
src/collective/lesscss/tool.py
src/collective/lesscss/browser/__init__.py
src/collective/lesscss/browser/compiledcss.py
src/collective/lesscss/browser/configure.zcml
src/collective/lesscss/browser/controlpanel.pt
src/collective/lesscss/browser/controlpanel.py
src/collective/lesscss/browser/interfaces.py
src/collective/lesscss/browser/less.pt
src/collective/lesscss/browser/less.py
src/collective/lesscss/browser/resourceregistries.pt
src/collective/lesscss/exportimport/__init__.py
src/collective/lesscss/exportimport/configure.zcml
src/collective/lesscss/exportimport/lessregistry.py
src/collective/lesscss/locales/collective.lesscss-manual.pot
src/collective/lesscss/locales/collective.lesscss.pot
src/collective/lesscss/locales/rebuild_i18n.sh
src/collective/lesscss/locales/es/LC_MESSAGES/collective.lesscss.po
src/collective/lesscss/profiles/default/browserlayer.xml
src/collective/lesscss/profiles/default/controlpanel.xml
src/collective/lesscss/profiles/default/jsregistry.xml
src/collective/lesscss/profiles/default/metadata.xml
src/collective/lesscss/profiles/default/registry.xml
src/collective/lesscss/profiles/default/skins.xml
src/collective/lesscss/profiles/default/toolset.xml
src/collective/lesscss/skins/lesscss/less.min.js
src/collective/lesscss/skins/lesscss/lessconfiglet.png
src/collective/lesscss/tests/__init__.py
src/collective/lesscss/tests/base.py
src/collective/lesscss/tests/test.zcml
src/collective/lesscss/tests/testExportImport.py
src/collective/lesscss/tests/testLESSRegistry.py
src/collective/lesscss/tests/skins/testskin/testlesssheet.less
src/collective/lesscss/tests/test_profile/lessregistry.xml
