Metadata-Version: 1.1
Name: collective.lesscss
Version: 2.0.2
Summary: This package allow theme developers to add LESS stylesheets into a Plone site.
Home-page: https://github.com/collective/collective.lesscss
Author: Victor Fernandez de Alba
Author-email: sneridagh@gmail.com
License: gpl
Keywords: plone zope less css
Platform: UNKNOWN
Classifier: Framework :: Plone
Classifier: Programming Language :: Python
